add_module/__init__.py
add_module/add.py
add_module-0.1.dist-info/LICENSE.txt
add_module-0.1.dist-info/METADATA
add_module-0.1.dist-info/WHEEL
add_module-0.1.dist-info/top_level.txt
add_module-0.1.dist-info/RECORD
