Metadata-Version: 2.1
Name: add-module
Version: 0.1
Summary: Python package for adding of 2 integer variables.
Home-page: UNKNOWN
Author: Santosh K
Author-email: santoshkdevp@gmail.com
License: UNKNOWN
Platform: UNKNOWN
License-File: LICENSE.txt
